investigator/__init__.py
investigator/base_models.py
investigator/github_client.py
investigator/policies.py
investigator/policy_engine.py
investigator/scoring.py
investigator/utils.py
investigator/checks/__init__.py
investigator/checks/basic_checks.py
investigator/checks/github_checks.py
investigator/queries/gh_query_org_repos.graphql
investigator/queries/gh_query_repo.graphql
investigator-1.4.0.dist-info/METADATA
investigator-1.4.0.dist-info/WHEEL
investigator-1.4.0.dist-info/licenses/LICENSE
investigator-1.4.0.dist-info/RECORD
