Metadata-Version: 2.4
Name: investigator
Version: 1.4.0
Summary: Retrieve and combine security statistics from popular web services
Author-email: T Torsteinbø <pypi@torsteinbo.no>
License-Expression: BSD-3-Clause
License-File: LICENSE
Requires-Python: >=3.12
Requires-Dist: cryptography>=46.0.3
Requires-Dist: pydash>=8.0.5
Requires-Dist: pyjwt>=2.10.1
Requires-Dist: requests>=2.32.5
